ws4redis/__init__.py
ws4redis/_compat.py
ws4redis/context_processors.py
ws4redis/django_runserver.py
ws4redis/exceptions.py
ws4redis/models.py
ws4redis/publisher.py
ws4redis/redis_store.py
ws4redis/settings.py
ws4redis/subscriber.py
ws4redis/utf8validator.py
ws4redis/uwsgi_runserver.py
ws4redis/websocket.py
ws4redis/wsgi_server.py
ws4redis/static/js/ws4redis.js
django_websocket_redis_plus-0.6.0.2.dist-info/LICENSE.txt
django_websocket_redis_plus-0.6.0.2.dist-info/METADATA
django_websocket_redis_plus-0.6.0.2.dist-info/WHEEL
django_websocket_redis_plus-0.6.0.2.dist-info/top_level.txt
django_websocket_redis_plus-0.6.0.2.dist-info/RECORD
