Metadata-Version: 2.1
Name: django-websocket-redis-plus
Version: 0.6.0.2
Summary: Websockets support for Django using Redis as datastore
Home-page: https://github.com/jrief/django-websocket-redis
Author: Jacob Rief
Author-email: jacob.rief@gmail.com
License: MIT
Keywords: django,websocket,redis
Platform: OS Independent
Classifier: Environment :: Web Environment
Classifier: Framework :: Django
Classifier: Framework :: Django :: 1.5
Classifier: Framework :: Django :: 1.6
Classifier: Framework :: Django :: 1.7
Classifier: Framework :: Django :: 1.8
Classifier: Framework :: Django :: 1.9
Classifier: Framework :: Django :: 2.0
Classifier: Framework :: Django :: 3.0
Classifier: Framework :: Django :: 3.1
Classifier: Framework :: Django :: 3.2
Classifier: Intended Audience :: Developers
Classifier: License :: OSI Approved :: MIT License
Classifier: Operating System :: OS Independent
Classifier: Programming Language :: Python
Classifier: Topic :: Software Development :: Libraries :: Python Modules
Classifier: Development Status :: 4 - Beta
Classifier: Programming Language :: Python :: 2.7
Classifier: Programming Language :: Python :: 3.5
Classifier: Programming Language :: Python :: 3.6
Classifier: Programming Language :: Python :: 3.7
Classifier: Programming Language :: Python :: 3.8
Classifier: Programming Language :: Python :: 3.9
License-File: LICENSE.txt
Requires-Dist: setuptools
Requires-Dist: redis
Requires-Dist: gevent
Requires-Dist: greenlet
Requires-Dist: six
Provides-Extra: django-redis-sessions
Requires-Dist: django-redis-sessions (>=0.4.0) ; extra == 'django-redis-sessions'
Provides-Extra: uwsgi
Requires-Dist: uWSGI (>=1.9.20) ; extra == 'uwsgi'
Provides-Extra: wsaccel
Requires-Dist: wsaccel (>=0.6.2) ; extra == 'wsaccel'
